cirq_iqm-17.0.dist-info/licenses/AUTHORS.rst
cirq_iqm-17.0.dist-info/licenses/LICENSE
iqm/cirq_iqm/__init__.py
iqm/cirq_iqm/extended_qasm_parser.py
iqm/cirq_iqm/iqm_gates.py
iqm/cirq_iqm/iqm_sampler.py
iqm/cirq_iqm/optimizers.py
iqm/cirq_iqm/py.typed
iqm/cirq_iqm/serialize.py
iqm/cirq_iqm/transpiler.py
iqm/cirq_iqm/devices/__init__.py
iqm/cirq_iqm/devices/adonis.py
iqm/cirq_iqm/devices/aphrodite.py
iqm/cirq_iqm/devices/apollo.py
iqm/cirq_iqm/devices/iqm_device.py
iqm/cirq_iqm/devices/iqm_device_metadata.py
cirq_iqm-17.0.dist-info/METADATA
cirq_iqm-17.0.dist-info/WHEEL
cirq_iqm-17.0.dist-info/top_level.txt
cirq_iqm-17.0.dist-info/RECORD
