Metadata-Version: 2.4
Name: cirq-iqm
Version: 17.0
Summary: Google Cirq adapter for IQM's quantum architectures
Author-email: IQM Finland Oy <developers@meetiqm.com>
License:                                  Apache License
Project-URL: homepage, https://github.com/iqm-finland/cirq-on-iqm
Project-URL: documentation, https://iqm-finland.github.io/cirq-on-iqm
Project-URL: repository, https://github.com/iqm-finland/cirq-on-iqm.git
Project-URL: changelog, https://github.com/iqm-finland/cirq-on-iqm/blob/main/CHANGELOG.rst
Classifier: Development Status :: 4 - Beta
Classifier: Programming Language :: Python :: 3 :: Only
Classifier: Topic :: Scientific/Engineering :: Physics
Classifier: Intended Audience :: Science/Research
Classifier: License :: OSI Approved :: Apache Software License
Requires-Python: <3.13,>=3.10
License-File: LICENSE
License-File: AUTHORS.rst
Requires-Dist: numpy
Requires-Dist: cirq-core[contrib]~=1.2
Requires-Dist: ply
Requires-Dist: iqm-client<23.0,>=22.0
Provides-Extra: dev
Requires-Dist: tox==4.11.4; extra == "dev"
Provides-Extra: docs
Requires-Dist: sphinx==7.2.6; extra == "docs"
Requires-Dist: sphinx-book-theme==1.1.2; extra == "docs"
Provides-Extra: testing
Requires-Dist: black==23.12.0; extra == "testing"
Requires-Dist: isort==5.13.2; extra == "testing"
Requires-Dist: jsons==1.4.2; extra == "testing"
Requires-Dist: mockito==1.4.0; extra == "testing"
Requires-Dist: mypy==1.7.1; extra == "testing"
Requires-Dist: pytest==7.4.3; extra == "testing"
Requires-Dist: pytest-cov==4.1.0; extra == "testing"
Requires-Dist: pytest-mockito==0.0.4; extra == "testing"
Requires-Dist: pytest-pylint==0.21.0; extra == "testing"
Dynamic: license-file
